setup.py
spout/__init__.py
spout/outputs.py
spout/queues.py
spout/sources.py
spout/streams.py
spout/structs.py
spout/utils.py
spout.egg-info/PKG-INFO
spout.egg-info/SOURCES.txt
spout.egg-info/dependency_links.txt
spout.egg-info/requires.txt
spout.egg-info/top_level.txt