Metadata-Version: 1.0
Name: spout
Version: 0.1.6
Summary: A simple framework that makes it easy to work with data streams in Python.
Home-page: http://github.com/daviesjamie/spout
Author: Jamie Davies
Author-email: jamie@jamiedavies.me
License: MIT
Platform: UNKNOWN
